pyeasee/__init__.py
pyeasee/__main__.py
pyeasee/charger.py
pyeasee/const.py
pyeasee/easee.py
pyeasee/exceptions.py
pyeasee/site.py
pyeasee/throttler.py
pyeasee/utils.py
pyeasee-0.8.16.dist-info/licenses/LICENSE
pyeasee-0.8.16.dist-info/METADATA
pyeasee-0.8.16.dist-info/WHEEL
pyeasee-0.8.16.dist-info/entry_points.txt
pyeasee-0.8.16.dist-info/top_level.txt
pyeasee-0.8.16.dist-info/RECORD
