Metadata-Version: 2.4
Name: pyeasee
Version: 0.8.16
Summary: Easee EV charger API library
Home-page: https://github.com/nordicopen/pyeasee
Author: Ola Lidholm
Author-email: olal@plea.se
License: MIT
Classifier: License :: OSI Approved :: MIT License
Classifier: Programming Language :: Python
Classifier: Programming Language :: Python :: 3
License-File: LICENSE
Requires-Dist: aiohttp
Requires-Dist: pysignalr==1.3.0
Dynamic: author
Dynamic: author-email
Dynamic: classifier
Dynamic: description
Dynamic: description-content-type
Dynamic: home-page
Dynamic: license
Dynamic: license-file
Dynamic: requires-dist
Dynamic: summary
